{
  "2025-06-15": [
    {
      "word": "einkaufen",
      "level": "B1"
    },
    {
      "word": "geschäfte",
      "level": "B1"
    },
    {
      "word": "jeden",
      "level": "A1"
    },
    {
      "word": "samstag",
      "level": "A2"
    },
    {
      "word": "öffnen",
      "level": "A2"
    },
    {
      "word": "läden",
      "level": "A1"
    },
    {
      "word": "innenstadt",
      "level": "B1"
    },
    {
      "word": "neun",
      "level": "A1"
    },
    {
      "word": "viele",
      "level": "A1"
    },
    {
      "word": "kunden",
      "level": "A2"
    },
    {
      "word": "warten",
      "level": "A2"
    },
    {
      "word": "schon",
      "level": "A1"
    },
    {
      "word": "geschäften",
      "level": "B1"
    },
    {
      "word": "erdgeschoss",
      "level": "B1"
    },
    {
      "word": "einkaufszentrums",
      "level": "B2"
    },
    {
      "word": "befinden",
      "level": "A2"
    },
    {
      "word": "sich",
      "level": "A1"
    },
    {
      "word": "kleine",
      "level": "A2"
    },
    {
      "word": "boutiquen",
      "level": "B1"
    },
    {
      "word": "kleidung",
      "level": "A2"
    },
    {
      "word": "schuhe",
      "level": "A2"
    },
    {
      "word": "verkäuferinnen",
      "level": "B2"
    },
    {
      "word": "beraten",
      "level": "A2"
    },
    {
      "word": "freundlich",
      "level": "B1"
    },
    {
      "word": "auswahl",
      "level": "A2"
    },
    {
      "word": "ersten",
      "level": "A2"
    },
    {
      "word": "etage",
      "level": "A1"
    },
    {
      "word": "gibt",
      "level": "A1"
    },
    {
      "word": "große",
      "level": "A1"
    },
    {
      "word": "buchabteilung",
      "level": "B2"
    },
    {
      "word": "hier",
      "level": "A1"
    },
    {
      "word": "stöbern",
      "level": "A2"
    },
    {
      "word": "leser",
      "level": "A1"
    },
    {
      "word": "zwischen",
      "level": "A2"
    },
    {
      "word": "romanen",
      "level": "A2"
    },
    {
      "word": "zeitschriften",
      "level": "B2"
    },
    {
      "word": "daneben",
      "level": "A2"
    },
    {
      "word": "liegt",
      "level": "A1"
    },
    {
      "word": "schreibwarenladen",
      "level": "B2"
    },
    {
      "word": "heften",
      "level": "A2"
    },
    {
      "word": "stiften",
      "level": "A2"
    },
    {
      "word": "bastelartikeln",
      "level": "B2"
    },
    {
      "word": "preise",
      "level": "A2"
    },
    {
      "word": "günstig",
      "level": "A2"
    },
    {
      "word": "qualität",
      "level": "A2"
    },
    {
      "word": "stimmt",
      "level": "A2"
    },
    {
      "word": "zweiten",
      "level": "A2"
    },
    {
      "word": "stock",
      "level": "A1"
    },
    {
      "word": "verkauft",
      "level": "A2"
    },
    {
      "word": "elektrohändler",
      "level": "B2"
    },
    {
      "word": "computer",
      "level": "A2"
    },
    {
      "word": "handys",
      "level": "A2"
    },
    {
      "word": "mitarbeiter",
      "level": "B1"
    },
    {
      "word": "erklären",
      "level": "A2"
    },
    {
      "word": "geduldig",
      "level": "A2"
    },
    {
      "word": "neuesten",
      "level": "A2"
    },
    {
      "word": "geräte",
      "level": "A2"
    },
    {
      "word": "viele",
      "level": "A1"
    },
    {
      "word": "angebote",
      "level": "A2"
    },
    {
      "word": "locken",
      "level": "A2"
    },
    {
      "word": "rabatten",
      "level": "A2"
    },
    {
      "word": "reparaturwerkstatt",
      "level": "B2"
    },
    {
      "word": "hilft",
      "level": "A1"
    },
    {
      "word": "technischen",
      "level": "B1"
    },
    {
      "word": "problemen",
      "level": "B1"
    },
    {
      "word": "drogeriemarkt",
      "level": "B2"
    },
    {
      "word": "untergeschoss",
      "level": "B2"
    },
    {
      "word": "bietet",
      "level": "A2"
    },
    {
      "word": "kosmetik",
      "level": "A2"
    },
    {
      "word": "hygieneartikel",
      "level": "B2"
    },
    {
      "word": "kasse",
      "level": "A1"
    },
    {
      "word": "stehen",
      "level": "A2"
    },
    {
      "word": "lange",
      "level": "A1"
    },
    {
      "word": "schlangen",
      "level": "B1"
    },
    {
      "word": "kunden",
      "level": "A2"
    },
    {
      "word": "packen",
      "level": "A2"
    },
    {
      "word": "ihre",
      "level": "A1"
    },
    {
      "word": "einkäufe",
      "level": "A2"
    },
    {
      "word": "taschen",
      "level": "A2"
    },
    {
      "word": "körbe",
      "level": "A1"
    },
    {
      "word": "beim",
      "level": "A1"
    },
    {
      "word": "bezahlen",
      "level": "A2"
    },
    {
      "word": "karte",
      "level": "A1"
    },
    {
      "word": "zahlen",
      "level": "A2"
    },
    {
      "word": "draußen",
      "level": "A2"
    },
    {
      "word": "marktplatz",
      "level": "B1"
    },
    {
      "word": "findet",
      "level": "A2"
    },
    {
      "word": "zweimal",
      "level": "A2"
    },
    {
      "word": "woche",
      "level": "A1"
    },
    {
      "word": "wochenmarkt",
      "level": "B1"
    },
    {
      "word": "statt",
      "level": "A1"
    },
    {
      "word": "bauern",
      "level": "A2"
    },
    {
      "word": "region",
      "level": "A2"
    },
    {
      "word": "verkaufen",
      "level": "B1"
    },
    {
      "word": "frische",
      "level": "A2"
    },
    {
      "word": "händler",
      "level": "A2"
    },
    {
      "word": "rufen",
      "level": "A1"
    },
    {
      "word": "laut",
      "level": "A1"
    },
    {
      "word": "ihre",
      "level": "A1"
    },
    {
      "word": "angebote",
      "level": "A2"
    },
    {
      "word": "stammkunden",
      "level": "B1"
    },
    {
      "word": "kennen",
      "level": "A2"
    },
    {
      "word": "besten",
      "level": "A2"
    },
    {
      "word": "stände",
      "level": "A2"
    },
    {
      "word": "nachmittag",
      "level": "B1"
    },
    {
      "word": "machen",
      "level": "A2"
    },
    {
      "word": "viele",
      "level": "A1"
    },
    {
      "word": "leute",
      "level": "A1"
    },
    {
      "word": "pause",
      "level": "A1"
    },
    {
      "word": "bestellen",
      "level": "B1"
    },
    {
      "word": "cappuccino",
      "level": "B1"
    },
    {
      "word": "schauen",
      "level": "A2"
    },
    {
      "word": "anderen",
      "level": "A2"
    },
    {
      "word": "besuchern",
      "level": "B1"
    },
    {
      "word": "kellner",
      "level": "A2"
    },
    {
      "word": "bringen",
      "level": "A2"
    },
    {
      "word": "kleine",
      "level": "A2"
    },
    {
      "word": "snacks",
      "level": "A2"
    },
    {
      "word": "gebäck",
      "level": "A2"
    },
    {
      "word": "atmosphäre",
      "level": "B1"
    },
    {
      "word": "entspannt",
      "level": "B1"
    },
    {
      "word": "gemütlich",
      "level": "B1"
    },
    {
      "word": "gegen",
      "level": "A1"
    },
    {
      "word": "abend",
      "level": "A1"
    },
    {
      "word": "schließen",
      "level": "B1"
    },
    {
      "word": "meisten",
      "level": "A2"
    },
    {
      "word": "läden",
      "level": "A1"
    },
    {
      "word": "kleine",
      "level": "A2"
    },
    {
      "word": "kiosk",
      "level": "A1"
    },
    {
      "word": "ecke",
      "level": "A1"
    },
    {
      "word": "länger",
      "level": "A2"
    },
    {
      "word": "geöffnet",
      "level": "A2"
    },
    {
      "word": "hier",
      "level": "A1"
    },
    {
      "word": "kaufen",
      "level": "A2"
    },
    {
      "word": "späte",
      "level": "A1"
    },
    {
      "word": "kunden",
      "level": "A2"
    },
    {
      "word": "zeitungen",
      "level": "B1"
    },
    {
      "word": "getränke",
      "level": "A2"
    },
    {
      "word": "freundliche",
      "level": "B1"
    },
    {
      "word": "besitzer",
      "level": "A2"
    },
    {
      "word": "kennt",
      "level": "A1"
    },
    {
      "word": "fast",
      "level": "A1"
    },
    {
      "word": "alle",
      "level": "A1"
    },
    {
      "word": "nachbarn",
      "level": "A2"
    }
  ]
}